{
  "__resolveType": "site/sections/Container.tsx",
  "sections": [
    {
      "section": {
        "__resolveType": "site/sections/Images/Carousel.tsx",
        "images": [
          {
            "action": {
              "variant": "primary",
              "href": "/s?q=kit+elegante"
            },
            "desktop": "https://ozksgdmyrqcxcwhnbepg.supabase.co/storage/v1/object/public/assets/8938/821a61ea-9768-439c-b7b7-164bbb5bd77a",
            "alt": "Condor",
            "mobile": "https://ozksgdmyrqcxcwhnbepg.supabase.co/storage/v1/object/public/assets/8938/348b0194-8403-480e-9a29-61469e2de905"
          },
          {
            "action": {
              "variant": "primary",
              "href": "/mormaiishop/relogios"
            },
            "desktop": "https://ozksgdmyrqcxcwhnbepg.supabase.co/storage/v1/object/public/assets/8938/60b42b8e-360f-4907-8669-79aa67dda773",
            "alt": "Mormaii",
            "mobile": "https://ozksgdmyrqcxcwhnbepg.supabase.co/storage/v1/object/public/assets/8938/a16be836-b2fb-46dc-8342-77cff3d2b563"
          },
          {
            "action": {
              "variant": "primary",
              "href": "/relogio?O=OrderByReleaseDateDESC"
            },
            "desktop": "https://ozksgdmyrqcxcwhnbepg.supabase.co/storage/v1/object/public/assets/8938/b135264c-9f63-4f38-96dd-8e0e2dcd50e0",
            "mobile": "https://ozksgdmyrqcxcwhnbepg.supabase.co/storage/v1/object/public/assets/8938/c1efae30-93e9-40d0-a426-01d2013bf3de",
            "alt": "Euro"
          },
          {
            "action": {
              "variant": "primary",
              "href": "https://www.timecenter.com.br/s?q=kid"
            },
            "desktop": "https://ozksgdmyrqcxcwhnbepg.supabase.co/storage/v1/object/public/assets/8938/2406fba1-9619-4b03-baf0-791bb7d83325",
            "mobile": "https://ozksgdmyrqcxcwhnbepg.supabase.co/storage/v1/object/public/assets/8938/6e821236-2c03-4c8c-a656-253f5d3f94dc",
            "alt": "Interativos"
          }
        ],
        "showPaginationArrows": "Desktop Only",
        "showPaginationDots": "Always",
        "interval": 5,
        "preload": true
      },
      "shadow": "none",
      "overFlow": "overflow-none",
      "verticalSpacing": "top",
      "label": "Carousel"
    }
  ],
  "label": "\"Container\""
}